{
  "name": "portal_ordem_cronologica",
  "owner_org": "",
  "profile": "data-package",
  "resources": [
    {
      "description": "Insira a descrição/explicação detalhada deste recurso.",
      "dialect": {
        "delimiter": ";"
      },
      "encoding": "utf-8-sig",
      "format": "csv",
      "hashing": "md5",
      "name": "ordemcronologica_2026",
      "path": "data/ordemcronologica_2026.csv",
      "profile": "tabular-data-resource",
      "schema": {
        "fields": [
          {
            "name": "ano",
            "type": "integer"
          },
          {
            "name": "codigo_unidade_orcamentaria",
            "type": "integer"
          },
          {
            "name": "nome_unidade_orcamentaria",
            "type": "string"
          },
          {
            "name": "codigo_unidade_executora",
            "type": "integer"
          },
          {
            "name": "funcional_programatica",
            "type": "string"
          },
          {
            "name": "codigo_elemento_despesa",
            "type": "integer"
          },
          {
            "name": "descricao_elemento_despesa",
            "type": "string"
          },
          {
            "name": "codigo_item_despesa",
            "type": "integer"
          },
          {
            "name": "descricao_item_despesa",
            "type": "string"
          },
          {
            "name": "codigo_fonte_recurso",
            "type": "integer"
          },
          {
            "name": "descricao_fonte_recurso",
            "type": "string"
          },
          {
            "name": "numero_empenho",
            "type": "integer"
          },
          {
            "name": "data_empenho",
            "type": "string"
          },
          {
            "name": "razao_social_credor",
            "type": "string"
          },
          {
            "name": "cnpj_cpf_credor",
            "type": "string"
          },
          {
            "name": "data_liquidacao",
            "type": "string"
          },
          {
            "name": "liquidacao_sequencial",
            "type": "integer"
          },
          {
            "name": "valor_despesa_liquidada",
            "type": "string"
          },
          {
            "name": "numero_op",
            "type": "integer"
          },
          {
            "name": "data_registro",
            "type": "string"
          },
          {
            "name": "data_pagamento",
            "type": "string"
          },
          {
            "name": "valor_pago_financeiro",
            "type": "string"
          },
          {
            "name": "quebra_sim_nao",
            "type": "any"
          },
          {
            "name": "justificativa",
            "type": "any"
          },
          {
            "name": "observacao_script",
            "type": "any"
          }
        ]
      },
      "scheme": "file",
      "title": "Insira um título humanamente legível para este recurso."
    },
    {
      "description": "Insira a descrição/explicação detalhada deste recurso.",
      "dialect": {
        "delimiter": ";"
      },
      "encoding": "utf-8-sig",
      "format": "csv",
      "hashing": "md5",
      "name": "pagamentos2026",
      "path": "data/pagamentos2026.csv",
      "profile": "tabular-data-resource",
      "schema": {
        "fields": [
          {
            "name": "ano",
            "type": "integer"
          },
          {
            "name": "codigo_unidade_orcamentaria",
            "type": "integer"
          },
          {
            "name": "nome_unidade_orcamentaria",
            "type": "string"
          },
          {
            "name": "codigo_unidade_executora",
            "type": "integer"
          },
          {
            "name": "funcional_programatica",
            "type": "string"
          },
          {
            "name": "codigo_elemento_despesa",
            "type": "integer"
          },
          {
            "name": "descricao_elemento_despesa",
            "type": "string"
          },
          {
            "name": "codigo_item_despesa",
            "type": "integer"
          },
          {
            "name": "descricao_item_despesa",
            "type": "string"
          },
          {
            "name": "codigo_fonte_recurso",
            "type": "integer"
          },
          {
            "name": "descricao_fonte_recurso",
            "type": "string"
          },
          {
            "name": "numero_empenho",
            "type": "integer"
          },
          {
            "name": "data_empenho",
            "type": "string"
          },
          {
            "name": "razao_social_credor",
            "type": "string"
          },
          {
            "name": "cnpj_cpf_credor",
            "type": "string"
          },
          {
            "name": "data_liquidacao",
            "type": "string"
          },
          {
            "name": "liquidacao_sequencial",
            "type": "integer"
          },
          {
            "name": "valor_despesa_liquidada",
            "type": "string"
          },
          {
            "name": "numero_op",
            "type": "integer"
          },
          {
            "name": "data_registro",
            "type": "string"
          },
          {
            "name": "data_pagamento",
            "type": "string"
          },
          {
            "name": "valor_pago_financeiro",
            "type": "string"
          },
          {
            "name": "quebra_sim_nao",
            "type": "any"
          },
          {
            "name": "justificativa",
            "type": "any"
          },
          {
            "name": "observacao_script",
            "type": "any"
          }
        ]
      },
      "scheme": "file",
      "title": "Insira um título humanamente legível para este recurso."
    }
  ],
  "title": "Portal_ordem_cronologica"
}